docassemble/webapp/__init__.py
docassemble/webapp/alembic.ini
docassemble/webapp/api_key.py
docassemble/webapp/app_object.py
docassemble/webapp/app_socket.py
docassemble/webapp/azure_mail.py
docassemble/webapp/backend.py
docassemble/webapp/cleanup_sessions.py
docassemble/webapp/clicksend.py
docassemble/webapp/cloud.py
docassemble/webapp/cloud_deregister.py
docassemble/webapp/cloud_register.py
docassemble/webapp/config_worker.py
docassemble/webapp/create_tables.py
docassemble/webapp/createminio.py
docassemble/webapp/cron.py
docassemble/webapp/da_flask_mail.py
docassemble/webapp/daredis.py
docassemble/webapp/database.py
docassemble/webapp/db_object.py
docassemble/webapp/deregister.py
docassemble/webapp/develop.py
docassemble/webapp/file_access.py
docassemble/webapp/file_number.py
docassemble/webapp/files.py
docassemble/webapp/fix_postgresql_tables.py
docassemble/webapp/fixpickle.py
docassemble/webapp/google_api.py
docassemble/webapp/info.py
docassemble/webapp/install_certs.py
docassemble/webapp/jsonstore.py
docassemble/webapp/list-cloud.py
docassemble/webapp/listlog.py
docassemble/webapp/logserver.py
docassemble/webapp/machinelearning.py
docassemble/webapp/mailgun_mail.py
docassemble/webapp/nltkdownload.py
docassemble/webapp/package_info.py
docassemble/webapp/playground.py
docassemble/webapp/process_email.py
docassemble/webapp/register.py
docassemble/webapp/restart.py
docassemble/webapp/run.py
docassemble/webapp/screenreader.py
docassemble/webapp/sendgrid_mail.py
docassemble/webapp/server.py
docassemble/webapp/setup.py
docassemble/webapp/socketserver.py
docassemble/webapp/socketstop.py
docassemble/webapp/sockettest.py
docassemble/webapp/spdx.py
docassemble/webapp/sqlalchemy_url.py
docassemble/webapp/starthook.py
docassemble/webapp/telnyx.py
docassemble/webapp/testrun.py
docassemble/webapp/translations.py
docassemble/webapp/update.py
docassemble/webapp/update_config.py
docassemble/webapp/user_database.py
docassemble/webapp/validators.py
docassemble/webapp/watchdog.py
docassemble_webapp-1.9.0.dist-info/licenses/LICENSE.txt
docassemble_webapp-1.9.0.dist-info/METADATA
docassemble_webapp-1.9.0.dist-info/WHEEL
docassemble_webapp-1.9.0.dist-info/top_level.txt
docassemble_webapp-1.9.0.dist-info/RECORD
